rftorch/__init__.py
rftorch/a2c/__init__.py
rftorch/a2c/agent.py
rftorch/a2c/example_main.py
rftorch/a2c/example_networks.py
rftorch/a2c/main.py
rftorch/a2c/utils.py
rftorch/ddpg/__init__.py
rftorch/ddpg/agent.py
rftorch/ddpg/example_main.py
rftorch/ddpg/example_networks.py
rftorch/ddpg/main.py
rftorch/ddpg/memory.py
rftorch/ddpg/noise.py
rftorch/ddpg/utils.py
rftorch/dqn/__init__.py
rftorch/dqn/agent.py
rftorch/dqn/example_main.py
rftorch/dqn/example_networks.py
rftorch/dqn/main.py
rftorch/dqn/memory.py
rftorch/dqn/utils.py
rftorch/ppo/__init__.py
rftorch/ppo/agent.py
rftorch/ppo/example_main.py
rftorch/ppo/example_networks.py
rftorch/ppo/main.py
rftorch/ppo/memory.py
rftorch/ppo/utils.py
rftorch-0.1.0.dist-info/LICENSE
rftorch-0.1.0.dist-info/METADATA
rftorch-0.1.0.dist-info/WHEEL
rftorch-0.1.0.dist-info/top_level.txt
rftorch-0.1.0.dist-info/RECORD
