Metadata-Version: 2.1
Name: rftorch
Version: 0.1.0
Summary: The minimalistic Deep Reinforcement Learning library written for PyTorch
Home-page: https://github.com/augcos/rftorch
Author: augcos
Author-email: augcos@protonmail.com
Project-URL: Bug Tracker, https://github.com/augcos/rftorch/issues
Classifier: Programming Language :: Python :: 3
Classifier: License :: OSI Approved :: MIT License
Classifier: Operating System :: OS Independent
Requires-Python: >=3.9
License-File: LICENSE
